fastapi_aad_auth/__init__.py
fastapi_aad_auth/_version.py
fastapi_aad_auth/auth.py
fastapi_aad_auth/config.py
fastapi_aad_auth/errors.py
fastapi_aad_auth/_base/__init__.py
fastapi_aad_auth/_base/backend.py
fastapi_aad_auth/_base/provider.py
fastapi_aad_auth/_base/state.py
fastapi_aad_auth/_base/authenticators/__init__.py
fastapi_aad_auth/_base/authenticators/session.py
fastapi_aad_auth/_base/validators/__init__.py
fastapi_aad_auth/_base/validators/base.py
fastapi_aad_auth/_base/validators/session.py
fastapi_aad_auth/_base/validators/token.py
fastapi_aad_auth/mixins/__init__.py
fastapi_aad_auth/mixins/logging.py
fastapi_aad_auth/mixins/not_authenticated.py
fastapi_aad_auth/oauth/__init__.py
fastapi_aad_auth/oauth/aad.py
fastapi_aad_auth/oauth/state.py
fastapi_aad_auth/providers/__init__.py
fastapi_aad_auth/providers/aad.py
fastapi_aad_auth/providers/ms-logo.png
fastapi_aad_auth/ui/__init__.py
fastapi_aad_auth/ui/base.html
fastapi_aad_auth/ui/error.html
fastapi_aad_auth/ui/jinja.py
fastapi_aad_auth/ui/login.html
fastapi_aad_auth/ui/user.html
fastapi_aad_auth/ui/static/__init__.py
fastapi_aad_auth/ui/static/css/__init__.py
fastapi_aad_auth/ui/static/css/bootstrap.min.css
fastapi_aad_auth/ui/static/css/bootstrap.min.css.map
fastapi_aad_auth/ui/static/css/cover.css
fastapi_aad_auth/ui/static/css/open-iconic-bootstrap.css
fastapi_aad_auth/ui/static/fonts/__init__.py
fastapi_aad_auth/ui/static/fonts/open-iconic.eot
fastapi_aad_auth/ui/static/fonts/open-iconic.otf
fastapi_aad_auth/ui/static/fonts/open-iconic.svg
fastapi_aad_auth/ui/static/fonts/open-iconic.ttf
fastapi_aad_auth/ui/static/fonts/open-iconic.woff
fastapi_aad_auth/utilities/__init__.py
fastapi_aad_auth/utilities/basemodel.py
fastapi_aad_auth/utilities/deprecate.py
fastapi_aad_auth/utilities/logging.py
fastapi_aad_auth/utilities/urls.py
fastapi_aad_auth-0.1.22.dist-info/LICENSE
fastapi_aad_auth-0.1.22.dist-info/METADATA
fastapi_aad_auth-0.1.22.dist-info/WHEEL
fastapi_aad_auth-0.1.22.dist-info/top_level.txt
fastapi_aad_auth-0.1.22.dist-info/RECORD
