Metadata-Version: 2.1
Name: fastapi-aad-auth
Version: 0.1.22
Summary: Provide Azure Active Directory Authentication for FastAPI
Home-page: https://djpugh.github.io/fastapi_aad_auth
Author: David Pugh
Author-email: djpugh@gmail.com
License: UNKNOWN
Platform: UNKNOWN
Classifier: Environment :: Console
Classifier: Topic :: Software Development :: Libraries :: Python Modules
Classifier: Topic :: Internet :: WWW/HTTP :: WSGI
Classifier: Programming Language :: Python :: 3
Classifier: Intended Audience :: Developers
Classifier: License :: OSI Approved :: MIT License
Classifier: Operating System :: Microsoft :: Windows
Classifier: Operating System :: POSIX :: Linux
Classifier: Operating System :: MacOS :: MacOS X
Classifier: Natural Language :: English
Classifier: Development Status :: 2 - Pre-Alpha
Provides: fastapi_aad_auth
Requires-Python: >=3
License-File: LICENSE
Requires-Dist: msal
Requires-Dist: aiofiles
Requires-Dist: jinja2 (>=2.11.3)
Requires-Dist: fastapi
Requires-Dist: authlib
Requires-Dist: cryptography (>=3.3.2)
Requires-Dist: python-multipart
Requires-Dist: requests
Requires-Dist: pydantic[dotenv]
Requires-Dist: itsdangerous
Requires-Dist: cachetools
